simple_pivot/__init__.py
simple_pivot/bins.py
simple_pivot/config.py
simple_pivot/exceptions.py
simple_pivot/log.py
simple_pivot/pivot.py
simple_pivot/source.py
simple_pivot/utils.py
simple_pivot-0.2.1.dist-info/METADATA
simple_pivot-0.2.1.dist-info/WHEEL
simple_pivot-0.2.1.dist-info/RECORD
