Metadata-Version: 2.1
Name: simple-pivot
Version: 0.2.1
Summary: Make pivots like in Excel
Home-page: https://github.com/ma-petrov/simple-pivot
License: MIT
Author: Petrov Mikhail
Author-email: petrov.ma@icloud.com
Requires-Python: >=3.9,<4.0
Classifier: License :: OSI Approved :: MIT License
Classifier: Programming Language :: Python :: 3
Classifier: Programming Language :: Python :: 3.9
Classifier: Programming Language :: Python :: 3.10
Classifier: Programming Language :: Python :: 3.11
Classifier: Programming Language :: Python :: 3.12
Requires-Dist: jinja2 (>=3.1.3,<4.0.0)
Requires-Dist: pandas (>=2.2.0,<3.0.0)
Requires-Dist: pydantic (>=2.6.1,<3.0.0)
